persunraveltorch/__init__.py
persunraveltorch/draw/__init__.py
persunraveltorch/draw/_read_template.py
persunraveltorch/draw/css-bkp/color_schemes.py
persunraveltorch/draw/css-bkp/polyline.py
persunraveltorch/draw/css.py
persunraveltorch/draw/draw.py
persunraveltorch/draw/seizing/__init__.py
persunraveltorch/draw/seizing/seizing.py
persunraveltorch/draw/seizing/sizes.py
persunraveltorch/draw/strip_orientation.py
persunraveltorch/draw/svg/__init__.py
persunraveltorch/draw/svg/background_creator.py
persunraveltorch/draw/svg/markers.py
persunraveltorch/draw/svg/strip_with_axes_pattern.py
persunraveltorch/draw/templates/dark-scheme.css
persunraveltorch/draw/templates/light-scheme.css
persunraveltorch/draw/templates/markers.svg
persunraveltorch/draw/templates/polyline.css
persunraveltorch/draw/viewbox.py
persunraveltorch/nn/__init__.py
persunraveltorch/nn/_glue_to_fragment.py
persunraveltorch/nn/_kernel_sizes.py
persunraveltorch/nn/biplane_from_intervals.py
persunraveltorch/nn/biplane_from_triangles.py
persunraveltorch/nn/conv_biplane.py
persunraveltorch/nn/functional/__init__.py
persunraveltorch/nn/functional/hilbert_kernel.py
persunraveltorch/nn/functional/max_pool_biplane.py
persunraveltorch/nn/functional/plane_select.py
persunraveltorch/nn/hilbert_gram.py
persunraveltorch/nn/hilbert_kernel.py
persunraveltorch/nn/max_pool_biplane.py
persunraveltorch/nn/plane_select.py
persunraveltorch/nn/raster_hilb_tria.py
persunraveltorch/nn/raster_triangle.py
persunraveltorch/nn/reshear.py
persunraveltorch/nn/strip_affine_functional-reshear-padding.py
persunraveltorch/nn/strip_affine_functional.py
persunraveltorch/nn/unravel.py
persunraveltorch-0.0.2.dist-info/METADATA
persunraveltorch-0.0.2.dist-info/WHEEL
persunraveltorch-0.0.2.dist-info/RECORD
